{"name":"searchBySingleKeyword","id":"starter.wikipedia.WhenSearchingForTerms:searchBySingleKeyword","testCaseName":"starter.wikipedia.WhenSearchingForTerms","testSteps":[{"number":1,"description":"Navigate to the home page","duration":7985,"startTime":"2021-12-14T02:34:54.435343526Z[Etc/UTC]","screenshots":[{"screenshot":"2ab8b904f3a42e87252dc7258ac76586e7c109af49f684f013fcad7ecd2a2881.png","timeStamp":1639449302419}],"result":"SUCCESS","precondition":false,"level":0},{"number":2,"description":"Search by keyword \u0027Everest\u0027","duration":1893,"startTime":"2021-12-14T02:35:02.425138049Z[Etc/UTC]","screenshots":[{"screenshot":"b6ef5f338a47b441ca7bb3fe688aaad54b65cc875ed9eb8f739eda0f6f1b68c9.png","timeStamp":1639449304318}],"result":"SUCCESS","precondition":false,"level":0},{"number":3,"description":"The first heading should be \u0027Mount Everest\u0027","duration":334,"startTime":"2021-12-14T02:35:04.319186597Z[Etc/UTC]","screenshots":[{"screenshot":"520d39a54f71b5bf6803cd811b3a5dd1064917b0da12c5751c3335bd5dc4aecd.png","timeStamp":1639449304653}],"result":"SUCCESS","precondition":false,"level":0}],"userStory":{"id":"starter.wikipedia.WhenSearchingForTerms","storyName":"When searching for terms","displayName":"When searching for terms","storyClassName":"starter.wikipedia.WhenSearchingForTerms","path":"wikipedia","type":"story"},"featureTag":{"name":"Wikipedia/When searching for terms","type":"story","displayName":"Wikipedia/When searching for terms"},"title":"Search by single keyword","tags":[{"name":"Wikipedia/When searching for terms","type":"story","displayName":"When searching for terms"},{"name":"Wikipedia","type":"feature","displayName":"Wikipedia"}],"startTime":"2021-12-14T02:34:54.311421925Z[Etc/UTC]","duration":10348,"projectKey":"","sessionId":"ac5d3051fcedf4f530c770b3a729ec81","driver":"chrome","isManualTestingUpToDate":false,"manual":false,"testSource":"JUnit5","order":0,"result":"SUCCESS"}